svg2turtle/__init__.py
svg2turtle/cli.py
svg2turtle/svg2turtle.py
svg2turtle-1.0.0.dist-info/METADATA
svg2turtle-1.0.0.dist-info/WHEEL
svg2turtle-1.0.0.dist-info/entry_points.txt
svg2turtle-1.0.0.dist-info/top_level.txt
svg2turtle-1.0.0.dist-info/RECORD
